datanator_query_python/VERSION
datanator_query_python/__init__.py
datanator_query_python/__main__.py
datanator_query_python/_version.py
datanator_query_python/core.py
datanator_query_python/config/__init__.py
datanator_query_python/config/config.py
datanator_query_python/config/query_manager.py
datanator_query_python/query/__init__.py
datanator_query_python/query/front_end_query.py
datanator_query_python/query/full_text_search.py
datanator_query_python/query/query_basic_users.py
datanator_query_python/query/query_corum.py
datanator_query_python/query/query_intact_complex.py
datanator_query_python/query/query_kegg_organism_code.py
datanator_query_python/query/query_kegg_orthology.py
datanator_query_python/query/query_metabolites.py
datanator_query_python/query/query_metabolites_meta.py
datanator_query_python/query/query_nosql.py
datanator_query_python/query/query_pax.py
datanator_query_python/query/query_protein.py
datanator_query_python/query/query_rna_halflife.py
datanator_query_python/query/query_sabio_compound.py
datanator_query_python/query/query_sabiork.py
datanator_query_python/query/query_sabiork_old.py
datanator_query_python/query/query_taxon_tree.py
datanator_query_python/query/query_uniprot.py
datanator_query_python/query/query_uniprot_org.py
datanator_query_python/query/query_xmdb.py
datanator_query_python/util/__init__.py
datanator_query_python/util/base26.py
datanator_query_python/util/chem_util.py
datanator_query_python/util/file_util.py
datanator_query_python/util/mongo_util.py
datanator_query_python-0.7.0.dist-info/LICENSE
datanator_query_python-0.7.0.dist-info/METADATA
datanator_query_python-0.7.0.dist-info/WHEEL
datanator_query_python-0.7.0.dist-info/entry_points.txt
datanator_query_python-0.7.0.dist-info/top_level.txt
datanator_query_python-0.7.0.dist-info/RECORD
